azure_blob_storage_cache/__init__.py
azure_blob_storage_cache/blob_cache.py
azure_blob_storage_cache/decorators.py
azure_blob_storage_cache/exceptions.py
azure_blob_storage_cache-0.2.0.dist-info/WHEEL
azure_blob_storage_cache-0.2.0.dist-info/METADATA
azure_blob_storage_cache-0.2.0.dist-info/RECORD
